{"session_file": "6285953872035", "phone": "6285953872035", "register_time": 1680355932, "app_id": 21724, "app_hash": "3e0cb5efcd52300aec5994fdfc5bdc16", "sdk": "SDK 18", "app_version": "9.1.4 (2927)", "device": "motorolaXT1068 titan_umtsds", "last_check_time": 1682083932, "avatar": true, "first_name": "TGBOSS", "last_name": "Accounts", "username": "agimunino7", "sex": 1, "lang_pack": "en", "system_lang_pack": "en-US", "twoFA": "agimunino7_5908084790", "ipv6": false, "status": "ok", "status_time": 1682083932, "is_old": false, "proxy": []}